{
  "basics": {
    "name": "Xuyang Wang (Rita)",
    "image": "",
    "email": "wxy.xuyang@gmail.com",
    "summary": "Graduate in Machine Learning and Computer Vision"
  },
  "work": [
    {
      "name": "XR Lab, Tencent",
      "position": "Research Intern",
      "startDate": "2022-08",
      "endDate": "2023-05",
      "summary": "Working on Virtual Avatar Generation for VR",
      "highlights": [
        "3D Human Reconstruction",
        "Motion Generation"
      ]
    },
    {
      "name": "Autonomous Driving Engineering Group, Baidu",
      "position": "Engineering Intern",
      "startDate": "2021-11",
      "endDate": "2022-01",
      "summary": "Working on 3D Point Cloud Tracking",
      "highlights": [
        "3D Point Clouds"
      ]
    }
  ],
  "volunteer": [],
  "education": [
    {
      "institution": "Australian National University, Canberra, Australia",
      "url": "https://cecc.anu.edu.au/",
      "area": "Machine Learning and Computer Vision",
      "studyType": "M.ENG",
      "startDate": "2021-07",
      "endDate": "2023-06",
      "score": "",
      "courses": [
        "Computer Vision",
        "Advanced Deep Learning for Computer Vision",
        "Statistic Machine Learning",
        "Engineering Data Analysis",
        "Document Analysis"
      ]
    },
    {
      "institution": "University of Sydney, Sydney, Australia",
      "url": "https://www.sydney.edu.au/engineering/schools/school-of-electrical-and-information-engineering.html",
      "area": "Bachelor of Engineering Honors",
      "studyType": "B.ENG (Honor)",
      "startDate": "2018-07",
      "endDate": "2020-06",
      "score": "",
      "courses": [
        "Computer Engineering",
        "Telecommunication Engineering",
        "Electronic and Information Engineering"
      ]
    },
    {
      "institution": "Harbin Institute of Technology, Harbin, China",
      "url": "http://hitee.hit.edu.cn/",
      "area": "Bachelor of Electrical Engineering",
      "studyType": "B.ENG",
      "startDate": "2016-08",
      "endDate": "2020-06",
      "score": "",
      "courses": [
        "Electrical Engineering"
      ]
    }
  ],
  "awards": [],
  "certificates": [],
  "publications": [],
  "skills": [],
  "languages": [
    {
      "language": "Chinese",
      "fluency": "Native speaker"
    },
    {
      "language": "English",
      "fluency": "Fluent"
    }
  ],
  "interests": [],
  "references": [],
  "projects": []
}